setup.py
Rooot/Rooot.py
Rooot/__init__.py
Rooot.egg-info/PKG-INFO
Rooot.egg-info/SOURCES.txt
Rooot.egg-info/dependency_links.txt
Rooot.egg-info/top_level.txt