Metadata-Version: 1.1
Name: Rooot
Version: 0.0.1
Summary: Simple package that allows to do any root faster.
Home-page: UNKNOWN
Author: ProfMYK
Author-email: <mykomurcu1@gmail.com>
License: UNKNOWN
Keywords: python,math,root
Platform: UNKNOWN
Classifier: Development Status :: 1 - Planning
Classifier: Intended Audience :: Developers
Classifier: Programming Language :: Python :: 3
Classifier: Operating System :: Unix
Classifier: Operating System :: MacOS :: MacOS X
Classifier: Operating System :: Microsoft :: Windows
